{
  "testItems": [
    {
      "title": "efficiency",
      "name": "Efficiency能效检测",
      "introduction": [
        "通过专业的检测仪器对企业大型耗能设备(包括照明、电机、风机、水泵、空气压缩机等)进行能效检测，提供真实可信的检测报告。是一项以节约能源和保护环境为宗旨的检测。"
        ],
      "projects": [
        "通过能效检测，能清晰的了解能耗的分布，再根据实际测量的数据，按照国家“电机系统效能评价”程序和方法，对企业的耗能设备进行能效评估。通过能效评估，可以发现企业的节能机会和节能空间，为节能方案提供数据资料。能效评价还包括为企业建立适合企业实际状况的能源利用率评价指标，通过这些指标，企业可以跟国家、行业标准进行比较，了解企业设备的能源利用率的相对水平及绝对水平。为企业下一步节能改善提供依据。"
        ],
      "advantages": [
        "1. 目前公司获得了UL、Intertek、CSA、MET、TUV- RH 、TUV-SUD、SGS、NEMKO、FCC、IC等众多国际认证机构的资质认可，能为客户提供专业权威的一站式检测认证服务。",
        "2. 取得中国合格评定国家认可委员会（CNAS）和中国计量认证(CMA)认可；以及美国国家实验室自愿认可程序NVLAP的认可。",
        "3. 依据标准以及客户要求进行环境实验",
        "4. 根据法规指令进行ERP,MEPS,能源之星等能效认证测试",
        "5. 为客户提供各国法规、指令、标准分析及培训服务"
      ]
    },
    {
      "title": "safety",
      "name": "Safety安全检测",
      "introduction": [
        "国际市场上纷纷提出对出口产品安全性能的要求，欧洲、北美甚至其他亚洲国家针对安规提出了各自不同的标准，出口不同国家如何符合相应的安全标准成为企业目前一大难题。",
        "安全测试是测试产品在使用过程中可能给使用人带来的危害测试。安全测试的判断依据主要是安全指标是否达到要求，而不是产品功能是否丢失为判断依据。最简单的判断就是是否给使用人带来危险，比如机械伤害、跌倒、烫伤、烧伤、电击、划伤等对使用人的伤害。由于产品使用范围和性质不同，导致有不同的安全标准。",
        "安全强调的是对使用和维护人员的保护，是在使用电子产品方便同时，不让电子产品带来危险，同时允许设备部分或全部功能丧失。设备部分或全部功能丧失，但是不会对使用人员带来危险，那么安全设计则是合格的，尽管设备可能不能使用。这与电子产品功能设计考虑是不同的，常规电子产品设计主要考虑怎样实现功能和保持功能的完好，以及产品对环境的适应。安规是从安全规范方面来考虑电子产品，它的目的是使得产品更加安全。"
      ],
      "projects": [
        "输入测试、电容放电测试、稳定性测试、外壳受力测试、应力释放测试、电池充放电测试、耐压测试、异常测试等测试项目。",
        "1. 电子产品安规检测：IEC60950-1,IEC60065,IEC60335-1,IEC60598-1,UL1598,UL153,UL8750,UL1993,UL935",
        "2. 机械性能安规测试：EN/ISO 12100-1,EN/ISO 12100-2,EN ISO14121-1,EN 60204-1,EN ISO 13857,EN ISO 13849-1,EN ISO 13854,EN ISO 13732-1,EN982,EN983,EN ISO 3746,EN ISO 3744",
        "3. 医疗专标安规检测：IEC60601-1,IEC60601-2-27,IEC61010-1 ,IEC60601-2-46,IEC60601-2-40,IEC60601-2-38,IEC60601-2-35,IEC60601-2-49,IEC60601-2-30,IEC60601-2-25,EN1060-1-3,EN/ISO9919,EC11"
      ],
      "advantages": [
        "1. 输入测试、电容放电测试、稳定性测试、外壳受力测试、应力释放测试、电池充放电测试、耐压测试、异常测试等测试项目。",
        "2. 贝岭是UL中国区约十家U Club成员之一；",
        "3. 与TUV、ITS、SGS、NEMKO等知名权威机构保持多年的良好合作关系",
        "4. 项目工程师均具备5-10年以上的丰富经验。"
      ]
    },
    {
      "title": "emc",
      "name": "EMC电磁兼容检测",
      "introduction": [
        "电磁兼容性测试EMC(Electro Magnetic Compatibility)，是指设备或系统在其电磁环境中符合要求运行并不对其环境中的任何设备产生无法忍受的电磁干扰的能力。它涉及电子、电机、信息、通信等各类产品，随着上述产品在各个领域的广泛应用，除了使用者对电磁兼容性有质量要求外，各国政府也积极制定相关管控标准和规范。 EMC设计与EMC测试相辅相成。EMC设计的好坏要通过EMC测试来衡量。只有在产品的EMC设计和研制的全过程中，进行EMC的相容性预测和评估，才能及早发现可能存在的电磁干扰，并采取必要的抑制和防护措施，从而确保系统的电磁兼容性。否则，当产品定型或系统建成后再发现不兼容的问题，则需在人力、物力上花很大的代价去修改设计或采用补救的措施。然而，往往难以彻底的解决问题，而给系统的使用带来许多麻烦。"
        ],
      "projects": [
        "浪涌抗扰度、传导骚扰抗扰度、电压跌落、振铃波、谐波和中间谐波测试、直流跌落、谐波电流、电压闪烁、电源谐波/闪烁干扰测试、SAR测试"
        ],
      "advantages": [
        "拥有美国NVLAP授权实验室Lab code：600102-0",
        "标准六米高分布式光度计暗房，数据每年与美国NIST一致"
      ]
    },
    {
      "title": "RF",
      "name": "射频测试",
      "introduction": "射频测试是射频电流，它是一种高频交流变化电磁波的简称。",
      "projects": [
        "1. 发射功率测试(传导法辐射法)",
        "2. 发射瞬态功率测试",
        "3. 发射邻道与次邻道功率测试",
        "4. 发射宽带测试",
        "5. 发射须谱特性",
        "6. 发射频率误差相位误差",
        "7. 发射杂散测试(传导法、辐射法)",
        "8. 接收最大可用灵敏度",
        "9. 接受邻近通道选择",
        "10. 接收信号阻塞",
        "11. 接收同信道抑制",
        "12. 接收杂散响应抑制",
        "13. 接收互调响应抑制",
        "14. SAR测试"
      ],
      "advantages": [
        "与TUV、ITS、SGS、NEMKO等知名权威机构保持多年的良好合作关系"
        ]
    },
    {
      "title": "chemical",
      "name": "化学检测",
      "introduction": [
        "当今消费群体在追求产品实用和美观的同时，也逐渐将目光转移到产品的质量与安全上，我国对于在境内生产及销售的纺织品与皮革毛皮制品均制定了相关的强制性标准，以保障人民的安全健康；国际上对消费产品也有不同程度的化学物质限量要求，化学检测能够为产品质量严格把关，积极有效减少召回风险。",
        "1.R&S TS8997 (EN300328/EN301893/FCCpart15.247/FCC part15.407)",
        "2.R&S TS8980 (EN301511/EN301908/FCCpart22H/24E/27)",
        "3.HTW8613(EN300086/EN300113/EN300219/EN300296/FCCpart90/95/80)",
        "4.DAYS52(EN50360/EN50566/EN62479/EN62311/EN62209/FCCPart2.1093)"
      ],
      "advantages": [
        "化学检测拥有高水平、专业化、经验丰富的检测技术团队，能高效率、高标准完成重金属、禁用偶氮染料、甲醛、pH值等各种有毒有害物质检测"
        ],
      "projects": [
        "可分解致癌芳香胺染料（禁用偶氮染料）检测、甲醛检测、pH值检测、异味检测、重金属检测、领苯二甲酸酯检测。"
        ]
    },
    {
      "title": "laser",
      "name": "光生物激光测试",
      "introduction": [
        "当前全球能源短缺，伴随着LED照明技术的日益成熟以及飞速发展，人们对高性能照明产品和高质量照明环境的需求也在不断提升，各国为了规范LED照明这一新兴市场，纷纷推出了相关技术法规或标准，对LED照明产品的应用提出了强制性的认证要求。"
        ],
      "projects": [
        "检测标准：IEC/EN60825, IEC/EN62471。"
        ],
      "advantages": [
        "1.提供电磁兼容、安全、能效、化学物质及性能全面的检测认证服务；",
        "2.贝岭是UL中国区约十家U Club成员之一；",
        "3.获得众多国际认证机构的认可，测试报告具有国际公信力；",
        "4.全套的先进检测设备以及强大的工程技术团队支持。"
        ]
    },
    {
      "title": "reliability",
      "name": "可靠性测试",
      "introduction": [
        "环境可靠性试验就是为了评估产品在规定的寿命期间内，在预期的使用、运输或储存等所有环境下，保持功能可靠性而进行的活动，是产品在规定环境条件下和规定时间内，完成规定功能的能力。另外通过环境试验可以分析和验证各种环境因素对产品效能的影响程度及作用机理，并广泛应用于汽车、通讯、电子电器等产品类别。"
        ],
      "projects": [
        "气候环境--温湿度类:高温、低温、恒定湿热、交变湿热、温湿度组合循环、快速温变、冷热冲击、低气压(高度模拟)",
        "气候环境--光照类:UV紫外光试验、氙灯试验、金属卤素灯、碳弧灯",
        "机械环境:随机振动试验、正弦振动试验、共振搜寻与驻留、正弦+随机振动试验、随机+随机振动试验、机械冲击试验、碰撞试验、稳态加速度、跌落试验",
        "综合环境:温度+温度+振动、温度+温度+冲击、温度+度+碰撞、HALT/HASS/HASA、温度+温度+堆码、高压蒸煮",
        "防护等级:IP防护(防水、防尘)、IK防护(外界机械碰撞防护)",
        "生物及化学活性物质环境:盐雾试验、霉菌试验、气体腐蚀、耐化学试剂、人工汗液",
        "物理性能:耐化学试剂，附着力/耐磨/划痕，硬度，拉伸/抗压/屈服强度，弯折/摇摆插拨/扭矩，阴燃，落球冲击/摆锤冲击/冲击锤冲击，色牢度/色差，熔融指数/熔点，滚桶跌落/定向跌落/微跌，按键寿命，反射率/透过率/吸收率",
        "电性能:绝缘/耐压，接触电，接地电阻，温升，介电强度，静电ESD，晶体管V/曲线，噪声/音质，电/电容/电感测试，瞬断，充/放电"
      ],
      "advantages": [
        "资深工程师能快速有效的为客户提供可行方案，高效的现场测试安排。"
        ]
    },
    {
      "title": "battery",
      "name": "电池测试",
      "introduction": [
        "目前便携式电池已经广泛应用在了通讯类、存储类等电子产品上，而大部分的便携式电池又以锂电池或者镍电池为主，有可充电的也有不可充电的。无论哪种电池，其相关的安全事故几乎没有停止过，因此对电池进行安全性检测非常重要。"
        ],
      "projects": [
        "镍电池：如低倍率充电、机械冲击测试、振动测试、挤压测试等",
        "锂电池：挤压测试、绝缘电阻、振动测试、强制内部短路等",
        "GB 31241-2014便携式电子产品用锂离子电池和电池组 安全要求：常温外部短路（电芯）、高温外部短路（电芯）、温度循环等",
        "电池相关国际认证：CB认证（IEC62133-1:2017）、RCM认证（IEC32133 UN38.3）、CTIA认证（IEE1625,IEEE1725）等"
      ],
      "advantages": [
        "当前针对电池的安全检测标准在不断更新中，但基本安全测试模式已经成型，各种常见的检测项目也已经被广泛接纳和采用。"
        ]
    }
  ]
}
